dtms_client/DTMSClient.py
dtms_client/__init__.py
dtms_client-0.2.0.dist-info/METADATA
dtms_client-0.2.0.dist-info/WHEEL
dtms_client-0.2.0.dist-info/RECORD
