Metadata-Version: 2.1
Name: dtms-client
Version: 0.2.0
Summary: Client library for DTMS api
Author: Shahriyar Shawon
Author-email: ShahriyarShawon321@gmail.com
Requires-Python: >=3.10,<4.0
Classifier: Programming Language :: Python :: 3
Classifier: Programming Language :: Python :: 3.10
Classifier: Programming Language :: Python :: 3.11
Requires-Dist: attrs (>=22.2.0,<23.0.0)
Requires-Dist: cattrs (>=22.2.0,<23.0.0)
Requires-Dist: requests (>=2.28.2,<3.0.0)
Requires-Dist: yarl (>=1.8.2,<2.0.0)
